cdk_artifact/__init__.py
cdk_artifact/py.typed
cdk_artifact/_jsii/__init__.py
cdk_artifact/_jsii/cdk-codeartifact@1.1.1.jsii.tgz
cdk_codeartifact-1.1.1.dist-info/LICENSE
cdk_codeartifact-1.1.1.dist-info/METADATA
cdk_codeartifact-1.1.1.dist-info/WHEEL
cdk_codeartifact-1.1.1.dist-info/top_level.txt
cdk_codeartifact-1.1.1.dist-info/RECORD
